4bmux-demux/demux.v
module demux (s0,s1,I,en,y0,y1,y2,y3);
input s0,s1,I,en;
output y0,y1,y2,y3;
assign y0=(~s0)&(~s1)& I& en;
assign y1=(~s0)& s1& I& en;
assign y2=s0&(~s1)& I & en;
assign y3=s0& s1 & I & en;
endmodule

module tb();
reg s0,s1,I,en;
wire y0,y1,y2,y3;
demux aa (.y0(y0),.y1(y1),.y2(y2),.y3(y3),.I(I),.en(en),.s1(s0),.s0(s1));
initial begin
$dumpfile("demux.vcd");
$dumpvars;
$display("y0 | y1 | y2 | y3 | s1 | s2 | en | I");
$display("____________________________________");
$monitor("%b  | %b  | %b  | %b  | %b  | %b  | %b  | %b",y0,y1,y2,y3,s1,s0,en,I);

I=1'b1;en=1'b0;s1=1'b0;s0=1'b0;
#1
I=1'b1;en=1'b0;s1=1'b0;s0=1'b1;
#1
I=1'b1;en=1'b0;s1=1'b1;s0=1'b0;
#1
I=1'b1;en=1'b0;s1=1'b1;s0=1'b1;
#1
I=1'b0;en=1'b0;s1=1'b0;s0=1'b0;
#1
I=1'b0;en=1'b0;s1=1'b0;s0=1'b1;
#1
I=1'b0;en=1'b0;s1=1'b1;s0=1'b0;
#1
I=1'b0;en=1'b0;s1=1'b1;s0=1'b1;
#1
I=1'b1;en=1'b1;s1=1'b0;s0=1'b0;
#1
I=1'b1;en=1'b1;s1=1'b0;s0=1'b1;
#1
I=1'b1;en=1'b1;s1=1'b1;s0=1'b0;
#1
I=1'b1;en=1'b1;s1=1'b1;s0=1'b1;
#1
I=1'b0;en=1'b1;s1=1'b0;s0=1'b0;
#1
I=1'b0;en=1'b1;s1=1'b0;s0=1'b1;
#1
I=1'b0;en=1'b1;s1=1'b1;s0=1'b0;
#1
I=1'b0;en=1'b1;s1=1'b1;s0=1'b1;

$finish;
end
endmodule

4bmux-demux/demux.vcd
$date
	Mon Mar 19 10:15:33 2018
$end
$version
	Icarus Verilog
$end
$timescale
	1s
$end
$scope module tb $end
$var wire 1 ! y0 $end
$var wire 1 " y1 $end
$var wire 1 # y2 $end
$var wire 1 $ y3 $end
$var reg 1 % I $end
$var reg 1 & en $end
$var reg 1 ' s0 $end
$var reg 1 ( s1 $end
$scope module aa $end
$var wire 1 ) I $end
$var wire 1 * en $end
$var wire 1 + s0 $end
$var wire 1 , s1 $end
$var wire 1 ! y0 $end
$var wire 1 " y1 $end
$var wire 1 # y2 $end
$var wire 1 $ y3 $end
$upscope $end
$upscope $end
$enddefinitions $end
#0
$dumpvars
0,
0+
0*
1)
0(
0'
0&
1%
0$
0#
0"
0!
$end
#1
1'
1,
#2
0'
0,
1(
1+
#3
1'
1,
#4
0'
0,
0(
0+
0%
0)
#5
1'
1,
#6
0'
0,
1(
1+
#7
1'
1,
#8
1!
0$
0'
0,
0(
0+
1&
1*
1%
1)
#9
0!
1"
1'
1,
#10
1#
0"
0'
0,
1(
1+
#11
0#
1$
1'
1,
#12
0$
0'
0,
0(
0+
0%
0)
#13
1'
1,
#14
0'
0,
1(
1+
#15
1'
1,
