2bit-comparator/Comparator.v
module Two_b_comp(x,y,a,b,eq,gt,ls);
    output eq,gt,ls;
    input a,b,x,y;
    not n1(x1,x);not nn(y1,y);
    and g1(a1,a,x1);
    xnor g3(xno1,a,x);
    and g2(a2,b,y1,xno1);
    or g4(gt,a2,a1);
    xnor g5(a3,a,x);
    xnor g6(a4,b,y);
    and g7(eq,a3,a4);
    nor g8(ls,eq,gt);
endmodule
	
	
module tb_tm;
	
	reg a,b;
	reg x,y;
	
	wire ls;
	wire eq;
	wire gt;
	
	Two_b_comp uut (.a(a),.b(b),.x(x),.y(y),.ls(ls),.eq(eq),.gt(gt));
	initial begin
		$dumpfile("Comparator.vcd");
		$dumpvars;
		$display("ab | xy |A>B|A=B|A<B");	
		$monitor("%b%b | %b%b | %b | %b | %b",a,b,x,y,gt,eq,ls);
		
		
a=0;b=0;x=0;y=0;#5
a=0;b=0;x=0;y=1;#5
a=0;b=0;x=1;y=0;#5
a=0;b=0;x=1;y=1;#5
a=0;b=1;x=0;y=0;#5
a=0;b=1;x=0;y=1;#5
a=0;b=1;x=1;y=0;#5
a=0;b=1;x=1;y=1;#5
a=1;b=0;x=0;y=0;#5
a=1;b=0;x=0;y=1;#5
a=1;b=0;x=1;y=0;#5
a=1;b=0;x=1;y=1;#5
a=1;b=1;x=0;y=0;#5
a=1;b=1;x=0;y=1;#5
a=1;b=1;x=1;y=0;#5
a=1;b=1;x=1;y=1;#5
a=1;b=1;x=1;y=1;



	end
endmodule

2bit-comparator/Comparator.vcd
$date
	Sun Feb 18 15:40:25 2018
$end
$version
	Icarus Verilog
$end
$timescale
	1s
$end
$scope module tb_tm $end
$var wire 1 ! eq $end
$var wire 1 " gt $end
$var wire 1 # ls $end
$var reg 1 $ a $end
$var reg 1 % b $end
$var reg 1 & x $end
$var reg 1 ' y $end
$scope module uut $end
$var wire 1 ( a $end
$var wire 1 ) a1 $end
$var wire 1 * a2 $end
$var wire 1 + a3 $end
$var wire 1 , a4 $end
$var wire 1 - b $end
$var wire 1 ! eq $end
$var wire 1 " gt $end
$var wire 1 # ls $end
$var wire 1 . x $end
$var wire 1 / x1 $end
$var wire 1 0 xno1 $end
$var wire 1 1 y $end
$var wire 1 2 y1 $end
$upscope $end
$upscope $end
$enddefinitions $end
#0
$dumpvars
12
01
10
1/
0.
0-
1,
1+
0*
0)
0(
0'
0&
0%
0$
0#
0"
1!
$end
#5
1#
0!
02
0,
1'
11
#10
12
1,
0/
00
0+
0'
01
1&
1.
#15
02
0,
1'
11
#20
0#
1"
1*
12
1/
10
1+
0'
01
0&
0.
1%
1-
#25
0"
0*
1!
02
1,
1'
11
#30
1#
0!
12
0,
0/
00
0+
0'
01
1&
1.
#35
02
1,
1'
11
#40
0#
1"
1)
12
1/
0'
01
0&
0.
0%
0-
1$
1(
#45
02
0,
1'
11
#50
0"
0)
1!
12
1,
0/
10
1+
0'
01
1&
1.
#55
1#
0!
02
0,
1'
11
#60
0#
1"
1)
12
1/
00
0+
0'
01
0&
0.
1%
1-
#65
02
1,
1'
11
#70
0)
1*
12
0,
0/
10
1+
0'
01
1&
1.
#75
0"
0*
1!
02
1,
1'
11
